jaraco/site/__init__.py
jaraco/site/charts.py
jaraco/site/controllers.py
jaraco/site/landing.py
jaraco/site/projects.py
jaraco/site/resume.py
jaraco/site/run.py
jaraco/site/projecthoneypot/__init__.py
jaraco/site/projecthoneypot/croakysteel.py
jaraco/site/static/css/style.css
jaraco/site/static/images/blog.svg
jaraco/site/static/images/fosstodon.svg
jaraco/site/static/images/github.svg
jaraco/site/static/images/info.png
jaraco/site/static/images/keybase.svg
jaraco/site/static/images/linkedin.svg
jaraco/site/static/images/ok.png
jaraco/site/static/images/stackoverflow.svg
jaraco/site/static/images/twitter.svg
jaraco/site/static/resume-1.5.1/README
jaraco/site/static/resume-1.5.1/css/NOTICE
jaraco/site/static/resume-1.5.1/css/blueorange.css
jaraco/site/static/resume-1.5.1/css/compact.css
jaraco/site/static/resume-1.5.1/css/cssClasses.sh
jaraco/site/static/resume-1.5.1/css/cssClasses.txt
jaraco/site/static/resume-1.5.1/css/gray.css
jaraco/site/static/resume-1.5.1/css/original.css
jaraco/site/static/resume-1.5.1/css/professional.css
jaraco/site/static/resume-1.5.1/doc/index.html
jaraco/site/static/resume-1.5.1/doc/authors/index.html
jaraco/site/static/resume-1.5.1/doc/changelog/index.html
jaraco/site/static/resume-1.5.1/doc/copying/index.html
jaraco/site/static/resume-1.5.1/doc/install/index.html
jaraco/site/static/resume-1.5.1/doc/manual/manual.css
jaraco/site/static/resume-1.5.1/doc/manual/manual.html
jaraco/site/static/resume-1.5.1/doc/manual/manual.txt
jaraco/site/static/resume-1.5.1/doc/manual/html/appendixes.html
jaraco/site/static/resume-1.5.1/doc/manual/html/box-0.gif
jaraco/site/static/resume-1.5.1/doc/manual/html/box-1.gif
jaraco/site/static/resume-1.5.1/doc/manual/html/caret-l.gif
jaraco/site/static/resume-1.5.1/doc/manual/html/caret-r.gif
jaraco/site/static/resume-1.5.1/doc/manual/html/caret-t.gif
jaraco/site/static/resume-1.5.1/doc/manual/html/caret-u.gif
jaraco/site/static/resume-1.5.1/doc/manual/html/cssref.html
jaraco.site-7.1.0.dist-info/LICENSE
jaraco.site-7.1.0.dist-info/METADATA
jaraco.site-7.1.0.dist-info/WHEEL
jaraco.site-7.1.0.dist-info/top_level.txt
jaraco.site-7.1.0.dist-info/RECORD
